ghdl/__init__.py
ghdl/config.hy
ghdl/local.hy
ghdl/main.hy
ghdl/remote.hy
ghdl/schema.hy
ghdl/utils.hy
ghdl-0.4.13.data/scripts/ghdl
ghdl-0.4.13.data/scripts/ghdl-delete-repo
ghdl-0.4.13.dist-info/METADATA
ghdl-0.4.13.dist-info/WHEEL
ghdl-0.4.13.dist-info/top_level.txt
ghdl-0.4.13.dist-info/RECORD
