Metadata-Version: 2.4
Name: ghdl
Version: 0.4.13
Summary: Binary Manager for Github Releases
Author-email: Imran Khan <imran@khan.ovh>
License:                     GNU AFFERO GENERAL PUBLIC LICENSE
Requires-Python: <3.14,>=3.8
Requires-Dist: xtract==0.1a3
Requires-Dist: xdg>=4.0.1
Requires-Dist: python-dateutil>=2.8.1
Requires-Dist: docopt>=0.6.2
Requires-Dist: python-magic>=0.4.25
Requires-Dist: hyrule>=0.7.0
Requires-Dist: hy>=1.0.0
Requires-Dist: httpx>=0.27.0
